[
  {
    "responses": ["", "      0: Not at all.", "      1: It is permitted but regulated in ways that, in practice, favor groups allied with the government.", "      2: It is permitted without limit.", "      3: It is permitted but regulated in ways that, in practice, foster representation of diverse", "      perspectives."],
    "answer_type": "Multiple Choice",
    "citation": "Pemstein et al. (2018, V-Dem Working Paper Series 2018:21); V-Dem Codebook (see suggested citation at the top of this document).",
    "notes": "",
    "question": "In this election, were interest groups and individuals able to run paid campaign ads on national broadcast media?",
    "name": "v2elpaidig, *_osp, *_ord"
  }
]
