[
  {
    "responses": ["", "      0: Parties are not allowed.", "      1: It is impossible, or virtually impossible, for parties not affiliated with the government to", "      form (legally).", "      2: There are significant obstacles (e.g. party leaders face high levels of regular political harassment by authorities).", "      3: There are modest barriers (e.g. party leaders face occasional political harassment by authorities).", "      4: There are no substantial barriers."],
    "answer_type": "Multiple Choice",
    "citation": "Pemstein et al. (2018, V-Dem Working Paper Series 2018:21); V-Dem Codebook (see suggested citation at the top of this document).",
    "notes": "",
    "question": "How restrictive are the barriers to forming a party?",
    "name": "v2psbars, *_osp, *_ord"
  }
]
